aiox/__init__.py
aiox/abc_analysis.py
aiox/create_time_series.py
aiox/read_and_write.py
aiox/xyz_analysis.py
aiox-0.0.6.dist-info/LICENSE
aiox-0.0.6.dist-info/METADATA
aiox-0.0.6.dist-info/WHEEL
aiox-0.0.6.dist-info/top_level.txt
aiox-0.0.6.dist-info/RECORD
