Metadata-Version: 2.1
Name: aiox
Version: 0.0.6
Summary: AIOx
Home-page: https://github.com/aioneers/aiox
Author: AIO
Author-email: maintainer@aioneers.com
License: MIT
Download-URL: https://github.com/aioneers/aiox/tags
Platform: UNKNOWN
Classifier: Programming Language :: Python :: 3
Classifier: License :: OSI Approved :: MIT License
Classifier: Operating System :: OS Independent
Requires-Python: >=3.7
Requires-Dist: azure-identity
Requires-Dist: azure-keyvault
Requires-Dist: nbsphinx
Requires-Dist: numpy
Requires-Dist: numpydoc
Requires-Dist: openpyxl
Requires-Dist: pandas
Requires-Dist: pyarrow
Requires-Dist: pydata-sphinx-theme
Requires-Dist: pytest
Requires-Dist: scipy
